docapi.py
evesky_docapi-1.0.0.dist-info/licenses/LICENSE
evesky_docapi-1.0.0.dist-info/METADATA
evesky_docapi-1.0.0.dist-info/WHEEL
evesky_docapi-1.0.0.dist-info/top_level.txt
evesky_docapi-1.0.0.dist-info/RECORD
