Metadata-Version: 2.4
Name: evesky-docapi
Version: 1.0.0
Summary: DocAPI SDK - PDF/Image/Excel 변환 API
Author-email: EVESKY <support@evesky.net>
License: MIT
Project-URL: Homepage, https://pdf.evesky.net
Project-URL: Documentation, https://pdf.evesky.net/docs
Project-URL: Repository, https://github.com/evesky/docapi-python
Keywords: pdf,image,excel,api,sdk,converter
Classifier: Development Status :: 5 - Production/Stable
Classifier: License :: OSI Approved :: MIT License
Classifier: Programming Language :: Python :: 3
Classifier: Programming Language :: Python :: 3.8
Classifier: Programming Language :: Python :: 3.9
Classifier: Programming Language :: Python :: 3.10
Classifier: Programming Language :: Python :: 3.11
Classifier: Programming Language :: Python :: 3.12
Requires-Python: >=3.8
License-File: LICENSE
Requires-Dist: requests>=2.25.0
Dynamic: license-file
